xmipy/__init__.py
xmipy/errors.py
xmipy/logger.py
xmipy/py.typed
xmipy/utils.py
xmipy/xmi.py
xmipy/xmiwrapper.py
xmipy/timers/__init__.py
xmipy/timers/timer.py
xmipy/timers/timers.py
xmipy-1.5.0.dist-info/METADATA
xmipy-1.5.0.dist-info/WHEEL
xmipy-1.5.0.dist-info/licenses/LICENSE
xmipy-1.5.0.dist-info/RECORD
