Metadata-Version: 2.3
Name: xmipy
Version: 1.5.0
Summary: xmipy is an extension to the bmipy Python package
Project-URL: Documentation, https://deltares.github.io/xmipy/xmipy.html
Project-URL: Source, https://github.com/Deltares/xmipy
Author-email: Martijn Russcher <Martijn.Russcher@deltares.nl>, Julian Hofer <Julian.Hofer@deltares.nl>, "Joseph D. Hughes" <jdhughes@usgs.gov>
License: CC0
License-File: LICENSE
Keywords: BMI,Basic Model Interface
Classifier: Intended Audience :: Science/Research
Classifier: License :: CC0 1.0 Universal (CC0 1.0) Public Domain Dedication
Classifier: Topic :: Scientific/Engineering :: Hydrology
Requires-Python: >=3.9
Requires-Dist: bmipy
Requires-Dist: numpy
Provides-Extra: docs
Requires-Dist: pdoc; extra == 'docs'
Provides-Extra: lint
Requires-Dist: mypy; extra == 'lint'
Requires-Dist: ruff; extra == 'lint'
Provides-Extra: tests
Requires-Dist: flopy>=3.3.6; extra == 'tests'
Requires-Dist: pytest; extra == 'tests'
Requires-Dist: pytest-cov; extra == 'tests'
Requires-Dist: requests; extra == 'tests'
